LICENSE.rst
MANIFEST.in
README.rst
setup.cfg
setup.py
dtool_info/__init__.py
dtool_info/dataset.py
dtool_info/inventory.py
dtool_info/overlay.py
dtool_info/utils.py
dtool_info.egg-info/PKG-INFO
dtool_info.egg-info/SOURCES.txt
dtool_info.egg-info/dependency_links.txt
dtool_info.egg-info/entry_points.txt
dtool_info.egg-info/requires.txt
dtool_info.egg-info/top_level.txt
dtool_info/templates/dtool_report.html.j2