Metadata-Version: 1.1
Name: dtool-info
Version: 0.16.2
Summary: Dtool plugin for getting information about datasets
Home-page: https://github.com/jic-dtool/dtool-info
Author: Tjelvar Olsson
Author-email: tjelvar.olsson@gmail.com
License: MIT
Download-URL: https://github.com/jic-dtool/dtool-info/tarball/0.16.2
Platform: UNKNOWN
